CONTRIBUTING.rst
LICENSE
MANIFEST.in
README.md
setup.cfg
setup.py
docs/Makefile
docs/conf.py
docs/contributing.rst
docs/index.rst
docs/installation.rst
docs/make.bat
docs/usage.rst
tests/__init__.py
tests/test_webex_bot.py
webex_bot_ecoen66/__init__.py
webex_bot_ecoen66/exceptions.py
webex_bot_ecoen66/formatting.py
webex_bot_ecoen66/webex_bot.py
webex_bot_ecoen66.egg-info/PKG-INFO
webex_bot_ecoen66.egg-info/SOURCES.txt
webex_bot_ecoen66.egg-info/dependency_links.txt
webex_bot_ecoen66.egg-info/not-zip-safe
webex_bot_ecoen66.egg-info/requires.txt
webex_bot_ecoen66.egg-info/top_level.txt
webex_bot_ecoen66/cards/__init__.py
webex_bot_ecoen66/commands/__init__.py
webex_bot_ecoen66/commands/echo.py
webex_bot_ecoen66/commands/help.py
webex_bot_ecoen66/models/__init__.py
webex_bot_ecoen66/models/command.py
webex_bot_ecoen66/models/response.py
webex_bot_ecoen66/websockets/__init__.py
webex_bot_ecoen66/websockets/webex_websocket_client.py