Metadata-Version: 2.1
Name: webex_bot_ecoen66
Version: 0.4.3
Summary: Python package for a Webex Bot based on websockets.
Home-page: https://github.com/ecoen66/webex_bot
Author: Finbarr Brady
Author-email: finbarr.brady@gmail.com
License: MIT license
Keywords: webex_bot_ecoen66
Classifier: Development Status :: 2 - Pre-Alpha
Classifier: Intended Audience :: Developers
Classifier: License :: OSI Approved :: MIT License
Classifier: Natural Language :: English
Classifier: Programming Language :: Python :: 3.8
Classifier: Programming Language :: Python :: 3.9
Classifier: Programming Language :: Python :: 3.10
Classifier: Programming Language :: Python :: 3.11
Requires-Python: >=3.8
License-File: LICENSE
Requires-Dist: webexteamssdk==1.6.1
Requires-Dist: coloredlogs
Requires-Dist: websockets==11.0.3
Requires-Dist: backoff
